blocksparse/__init__.py
blocksparse/blocksparse_ops.so
blocksparse/conv.py
blocksparse/embed.py
blocksparse/ewops.py
blocksparse/grads.py
blocksparse/lstm.py
blocksparse/matmul.py
blocksparse/nccl.py
blocksparse/norms.py
blocksparse/optimize.py
blocksparse/quantize.py
blocksparse/transformer.py
blocksparse/utils.py
blocksparse-1.13.1.dist-info/DESCRIPTION.rst
blocksparse-1.13.1.dist-info/METADATA
blocksparse-1.13.1.dist-info/RECORD
blocksparse-1.13.1.dist-info/WHEEL
blocksparse-1.13.1.dist-info/metadata.json
blocksparse-1.13.1.dist-info/top_level.txt
